study_and_revise/__init__.py
study_and_revise/sr.py
study_and_revise-0.1.11.dist-info/LICENSE.txt
study_and_revise-0.1.11.dist-info/METADATA
study_and_revise-0.1.11.dist-info/WHEEL
study_and_revise-0.1.11.dist-info/entry_points.txt
study_and_revise-0.1.11.dist-info/top_level.txt
study_and_revise-0.1.11.dist-info/RECORD
