Metadata-Version: 2.1
Name: study-and-revise
Version: 0.1.11
Summary: study and revise
Author: txs
Author-email: c3qu@qq.com
Classifier: Programming Language :: Python :: 3
Classifier: License :: OSI Approved :: GNU General Public License v3 (GPLv3)
Classifier: Operating System :: OS Independent
Requires-Python: >=3.0
License-File: LICENSE.txt
